[
  [
    {
      "greek_title": "Το 47",
      "original_title": "El 47",
      "athinorama_link": "https://www.athinorama.gr/cinema/movie/to_47-10086638"
    }
  ],
  [
    {
      "greek_title": "Αγάπη Μόνο",
      "original_title": "Kjærlighet / Love",
      "athinorama_link": "https://www.athinorama.gr/cinema/movie/agapi_mono-10087322"
    }
  ],
  [
    {
      "greek_title": "Άλπεις",
      "original_title": "",
      "athinorama_link": "https://www.athinorama.gr/cinema/movie/alpeis-10009258"
    }
  ],
  [
    {
      "greek_title": "Αμυγδαλιά",
      "original_title": "",
      "athinorama_link": "https://www.athinorama.gr/cinema/movie/amugdalia-10068525"
    }
  ],
  [
    {
      "greek_title": "Ο Άνθρωπος με το Χρυσό Χέρι",
      "original_title": "The Man With the Golden Arm",
      "athinorama_link": "https://www.athinorama.gr/cinema/movie/o_anthropos_me_to_xruso_xeri-10048555"
    }
  ],
  [
    {
      "greek_title": "Ο Άνθρωπος Χωρίς Παρελθόν",
      "original_title": "Mies Vailla Menneisyyttä / The Man Without a Past",
      "athinorama_link": "https://www.athinorama.gr/cinema/movie/o_anthropos_xoris_parelthon-1006824"
    }
  ],
  [
    {
      "greek_title": "Ο Αστακός",
      "original_title": "The Lobster",
      "athinorama_link": "https://www.athinorama.gr/cinema/movie/o_astakos-10049281"
    }
  ],
  [
    {
      "greek_title": "Αχινός",
      "original_title": "Urchin",
      "athinorama_link": "https://www.athinorama.gr/cinema/movie/axinos-10087613"
    }
  ],
  [
    {
      "greek_title": "Βαμπίρ",
      "original_title": "Vampyr",
      "athinorama_link": "https://www.athinorama.gr/cinema/movie/bampir-10032849"
    }
  ],
  [
    {
      "greek_title": "Good Boy",
      "original_title": "",
      "athinorama_link": "https://www.athinorama.gr/cinema/movie/good_boy-10087321"
    }
  ],
  [
    {
      "greek_title": "Η Γυναίκα με τα Σπίρτα",
      "original_title": "The Match Factory Girl",
      "athinorama_link": "https://www.athinorama.gr/cinema/movie/i_gunaika_me_ta_spirta-1004219"
    }
  ],
  [
    {
      "greek_title": "Ένα Απλό Ατύχημα",
      "original_title": "Yek Tasadef Sadeh / It Was Just An Accident",
      "athinorama_link": "https://www.athinorama.gr/cinema/movie/ena_aplo_atuxima-10087413"
    }
  ],
  [
    {
      "greek_title": "Εξολοθρευτής Άγγελος",
      "original_title": "El Angel Exterminador",
      "athinorama_link": "https://www.athinorama.gr/cinema/movie/eksolothreutis_aggelos-1007248"
    }
  ],
  [
    {
      "greek_title": "Έρωτας στη Βαρκελώνη",
      "original_title": "Mi Amiga Eva",
      "athinorama_link": "https://www.athinorama.gr/cinema/movie/erotas_sti_barkeloni-10087053"
    }
  ],
  [
    {
      "greek_title": "F1: Η Ταινία",
      "original_title": "F1: The Movie",
      "athinorama_link": "https://www.athinorama.gr/cinema/movie/f1_i_tainia_-10086559"
    }
  ],
  [
    {
      "greek_title": "Εφιάλτης στο Δρόμο με τις Λεύκες",
      "original_title": "Nightmare on Elm Street",
      "athinorama_link": "https://www.athinorama.gr/cinema/movie/efialtis_sto_dromo_me_tis_leukes-1000080"
    }
  ],
  [
    {
      "greek_title": "Ο Θάνατος του Ιερού Ελαφιού",
      "original_title": "The Killing of a Sacred Deer",
      "athinorama_link": "https://www.athinorama.gr/cinema/movie/o_thanatos_tou_ierou_elafiou-10058117"
    }
  ],
  [
    {
      "greek_title": "Interstellar",
      "original_title": "",
      "athinorama_link": "https://www.athinorama.gr/cinema/movie/interstellar-10040927"
    }
  ],
  [
    {
      "greek_title": "Ιστορίες του Σηκουάνα",
      "original_title": "La Belle Équipe",
      "athinorama_link": "https://www.athinorama.gr/cinema/movie/istories_tou_sikouana-10087194"
    }
  ],
  [
    {
      "greek_title": "Καίτη Δρόσου: Κιβώτιο Μνήμης",
      "original_title": "",
      "athinorama_link": "https://www.athinorama.gr/cinema/movie/kaiti_drosou_kibotio_mnimis-10087669"
    }
  ],
  [
    {
      "greek_title": "Τα Κακά Παιδιά 2",
      "original_title": "The Bad Guys 2",
      "athinorama_link": "https://www.athinorama.gr/cinema/movie/ta_kaka_paidia_2-10086927"
    }
  ],
  [
    {
      "greek_title": "Καλές Γιορτές",
      "original_title": "Happy Holidays",
      "athinorama_link": "https://www.athinorama.gr/cinema/movie/kales_giortes-10087398"
    }
  ],
  [
    {
      "greek_title": "Το Κάλεσμα 4: Τελευταία Τελετουργία",
      "original_title": "Conjuring: Last Rites",
      "athinorama_link": "https://www.athinorama.gr/cinema/movie/to_kalesma_4_teleutaia_teletourgia-10086923"
    }
  ],
  [
    {
      "greek_title": "Η Κατάρα του Σέλμπι Όουκς",
      "original_title": "Shelby Oaks",
      "athinorama_link": "https://www.athinorama.gr/cinema/movie/i_katara_tou_selmpi_oouks-10087454"
    }
  ],
  [
    {
      "greek_title": "Κατοικίδια στο Express",
      "original_title": "Falcon Express / Pets on a Train",
      "athinorama_link": "https://www.athinorama.gr/cinema/movie/katoikidia_sto_express-10087297"
    }
  ],
  [
    {
      "greek_title": "Κλέφτης από Σπόντα",
      "original_title": "Caught Stealing",
      "athinorama_link": "https://www.athinorama.gr/cinema/movie/kleftis_apo_sponta-10086921"
    }
  ],
  [
    {
      "greek_title": "Το Κουκλόσπιτο της Γκάμπι: Η Ταινία",
      "original_title": "Gabby's Dollhouse: The Movie",
      "athinorama_link": "https://www.athinorama.gr/cinema/movie/to_kouklospito_tis_gkampi_i_tainia-10087197"
    }
  ],
  [
    {
      "greek_title": "Κυνήγι",
      "original_title": "",
      "athinorama_link": "https://www.athinorama.gr/cinema/movie/kunigi-10084914"
    }
  ],
  [
    {
      "greek_title": "Leningrad Cowboys Meet Moses",
      "original_title": "",
      "athinorama_link": "https://www.athinorama.gr/cinema/movie/leningrad_cowboys_meet_moses-10087549"
    }
  ],
  [
    {
      "greek_title": "Λίλο & Στιτς",
      "original_title": "Lilo & Stitch",
      "athinorama_link": "https://www.athinorama.gr/cinema/movie/lilo_kai_stits-10086191"
    }
  ],
  [
    {
      "greek_title": "Το Λιμάνι της Χάβρης",
      "original_title": "Le Havre",
      "athinorama_link": "https://www.athinorama.gr/cinema/movie/to_limani_tis_xabris-10011569"
    }
  ],
  [
    {
      "greek_title": "Melancholia",
      "original_title": "",
      "athinorama_link": "https://www.athinorama.gr/cinema/movie/melancholia-10008310"
    }
  ],
  [
    {
      "greek_title": "Μέρες Οργής",
      "original_title": "Day of Wrath / Vredens Dag",
      "athinorama_link": "https://www.athinorama.gr/cinema/movie/meres_orgis-10032800"
    }
  ],
  [
    {
      "greek_title": "Merrily We Go to Hell",
      "original_title": "",
      "athinorama_link": "https://www.athinorama.gr/cinema/movie/merrily_we_go_to_hell-10087660"
    }
  ],
  [
    {
      "greek_title": "Μετά το Κυνήγι",
      "original_title": "After the Hunt",
      "athinorama_link": "https://www.athinorama.gr/cinema/movie/meta_to_kunigi-10087455"
    }
  ],
  [
    {
      "greek_title": "Μια Μάχη Μετά την Άλλη",
      "original_title": "One Battle After Another",
      "athinorama_link": "https://www.athinorama.gr/cinema/movie/mia_maxi_meta_tin_alli-10087181"
    }
  ],
  [
    {
      "greek_title": "Το Μίσος",
      "original_title": "La Haine",
      "athinorama_link": "https://www.athinorama.gr/cinema/movie/to_misos-1005102"
    }
  ],
  [
    {
      "greek_title": "Mitski: The Land",
      "original_title": "",
      "athinorama_link": "https://www.athinorama.gr/cinema/movie/mitski_the_land-10087661"
    }
  ],
  [
    {
      "greek_title": "Μπερλινγκουέρ: Η Μεγάλη Ελπίδα",
      "original_title": "Berlinguer: La Grande Ambizione",
      "athinorama_link": "https://www.athinorama.gr/cinema/movie/mperlingkouer_i_megali_elpida-10087192"
    }
  ],
  [
    {
      "greek_title": "Μποέμικη Ζωή",
      "original_title": "La Vie de Bohème",
      "athinorama_link": "https://www.athinorama.gr/cinema/movie/mpoemiki_zoi-1004789"
    }
  ],
  [
    {
      "greek_title": "Ο Νάτζι Αλ-Αλί στην Αγκαλιά του Χαντάλα",
      "original_title": "Naji Al-Ali: In the Embrace of Handala",
      "athinorama_link": "https://www.athinorama.gr/cinema/movie/o_natzi_al_ali_stin_agkalia_tou_xantala-10087330"
    }
  ],
  [
    {
      "greek_title": "Ne Zha 2",
      "original_title": "",
      "athinorama_link": "https://www.athinorama.gr/cinema/movie/ne_zha_2-10087260"
    }
  ],
  [
    {
      "greek_title": "Νεκρό Τηλέφωνο 2",
      "original_title": "Black Phone 2",
      "athinorama_link": "https://www.athinorama.gr/cinema/movie/nekro_tilefono_2-10087456"
    }
  ],
  [
    {
      "greek_title": "Demolition Man",
      "original_title": "",
      "athinorama_link": "https://www.athinorama.gr/cinema/movie/demolition_man-1004768"
    }
  ],
  [
    {
      "greek_title": "Depeche Mode: M",
      "original_title": "",
      "athinorama_link": "https://www.athinorama.gr/cinema/movie/depeche_mode_m-10087662"
    }
  ],
  [
    {
      "greek_title": "Demon Slayer: Kimetsu no Yaiba - Το Κάστρο του Άπειρου",
      "original_title": "Gekijô-ban Kimetsu no Yaiba Mugen Jô-hen / Demon Slayer: Kimetsu no Yaiba - Infinity Castle",
      "athinorama_link": "https://www.athinorama.gr/cinema/movie/demon_slayer_kimetsu_no_yaiba___to_kastro_tou_apeirou-10087025"
    }
  ],
  [
    {
      "greek_title": "Dracula",
      "original_title": "Dracula: A Love Tale",
      "athinorama_link": "https://www.athinorama.gr/cinema/movie/dracula-10087251"
    }
  ],
  [
    {
      "greek_title": "Το Ξύσιμο των Νεκρών",
      "original_title": "Shaun of the Dead",
      "athinorama_link": "https://www.athinorama.gr/cinema/movie/to_ksusimo_ton_nekron-10087547"
    }
  ],
  [
    {
      "greek_title": "Όλα για τη Μητέρα Μου",
      "original_title": "Todo Sobre Mi Madre",
      "athinorama_link": "https://www.athinorama.gr/cinema/movie/ola_gia_ti_mitera_mou-1006057"
    }
  ],
  [
    {
      "greek_title": "Οπενχάιμερ",
      "original_title": "Oppenheimer",
      "athinorama_link": "https://www.athinorama.gr/cinema/movie/openxaimer-10078898"
    }
  ],
  [
    {
      "greek_title": "Όσο θα Υπάρχει ο Κόσμος",
      "original_title": "On the Beach",
      "athinorama_link": "https://www.athinorama.gr/cinema/movie/oso_tha_uparxei_o_kosmos-10087663"
    }
  ],
  [
    {
      "greek_title": "Όταν Έρθει το Φθινόπωρο",
      "original_title": "Quand Vient l'Automne",
      "athinorama_link": "https://www.athinorama.gr/cinema/movie/otan_erthei_to_fthinoporo-10086757"
    }
  ],
  [
    {
      "greek_title": "Τα Παιδιά του Παραδείσου",
      "original_title": "Les Enfants du Paradis",
      "athinorama_link": "https://www.athinorama.gr/cinema/movie/ta_paidia_tou_paradeisou-10008792"
    }
  ],
  [
    {
      "greek_title": "Τα Παιδιά των Ανθρώπων",
      "original_title": "Children of Men",
      "athinorama_link": "https://www.athinorama.gr/cinema/movie/ta_paidia_ton_anthropon-1008036"
    }
  ],
  [
    {
      "greek_title": "Η Πέππα Γνωρίζει το Νέο Μωρό",
      "original_title": "Peppa Meets The Baby Cinema Experience",
      "athinorama_link": "https://www.athinorama.gr/cinema/movie/i_peppa_gnorizei_to_neo_moro-10087294"
    }
  ],
  [
    {
      "greek_title": "Πεσμένα Φύλλα",
      "original_title": "Kuolleet Lehdet / Fallen Leaves",
      "athinorama_link": "https://www.athinorama.gr/cinema/movie/pesmena_fulla-10080013"
    }
  ],
  [
    {
      "greek_title": "Poor Things",
      "original_title": "",
      "athinorama_link": "https://www.athinorama.gr/cinema/movie/poor_things-10080313"
    }
  ],
  [
    {
      "greek_title": "Προσέλαβα Έναν Επαγγελματία Δολοφόνο",
      "original_title": "I Hired A Contract Killer",
      "athinorama_link": "https://www.athinorama.gr/cinema/movie/proselaba_enan_epaggelmatia_dolofono-1004362"
    }
  ],
  [
    {
      "greek_title": "Ρίφενσταλ: Στην Καρδιά του Τρίτου Ράιχ",
      "original_title": "Riefenstahl",
      "athinorama_link": "https://www.athinorama.gr/cinema/movie/rifenstal_stin_kardia_tou_tritou_raix-10087457"
    }
  ],
  [
    {
      "greek_title": "The Smashing Machine: Η Καρδιά Ενός Μαχητή",
      "original_title": "The Smashing Machine",
      "athinorama_link": "https://www.athinorama.gr/cinema/movie/the_smashing_machine_i_kardia_enos_maxiti-1004727"
    }
  ],
  [
    {
      "greek_title": "Sorry, Baby",
      "original_title": "",
      "athinorama_link": "https://www.athinorama.gr/cinema/movie/sorry_baby-10086724"
    }
  ],
  [
    {
      "greek_title": "Super Paradise",
      "original_title": "",
      "athinorama_link": "https://www.athinorama.gr/cinema/movie/super_paradise-10087458"
    }
  ],
  [
    {
      "greek_title": "Springsteen: Deliver Me from Nowhere",
      "original_title": "",
      "athinorama_link": "https://www.athinorama.gr/cinema/movie/springsteen_deliver_me_from_nowhere-10087614"
    }
  ],
  [
    {
      "greek_title": "Στα Βάθη του Χειμώνα",
      "original_title": "Dead of Winter",
      "athinorama_link": "https://www.athinorama.gr/cinema/movie/sta_bathi_tou_xeimona-10087302"
    }
  ],
  [
    {
      "greek_title": "Συναισθηματική Αξία",
      "original_title": "Affeksjonsverdi / Sentimental Value",
      "athinorama_link": "https://www.athinorama.gr/cinema/movie/sunaisthimatiki_aksia-10087020"
    }
  ],
  [
    {
      "greek_title": "Τα Τέρματα του Αυγούστου",
      "original_title": "",
      "athinorama_link": "https://www.athinorama.gr/cinema/movie/ta_termata_tou_augoustou-10087607"
    }
  ],
  [
    {
      "greek_title": "Τομ και Τζέρι: Η Απαγορευμένη Πυξίδα",
      "original_title": "Mâo Hé Lâoshâ: Xîng Pán Qí Yuán / Tom and Jerry: Forbidden Compass",
      "athinorama_link": "https://www.athinorama.gr/cinema/movie/tom_kai_tzeri_i_apagoreumeni_puksida-10087615"
    }
  ],
  [
    {
      "greek_title": "Tron: Ares",
      "original_title": "",
      "athinorama_link": "https://www.athinorama.gr/cinema/movie/tron_ares-10087296"
    }
  ],
  [
    {
      "greek_title": "Chainsaw Man – Η Ταινία: Reze Arc",
      "original_title": "Gekijô-ban Chensô Man Reze-hen / Chainsaw Man – The Movie: Reze Arc",
      "athinorama_link": "https://www.athinorama.gr/cinema/movie/chainsaw_man_–_i_tainia_reze_arc-10087608"
    }
  ],
  [
    {
      "greek_title": "Τύχη Βουνό",
      "original_title": "Good Fortune",
      "athinorama_link": "https://www.athinorama.gr/cinema/movie/tuxi_bouno-10087459"
    }
  ],
  [
    {
      "greek_title": "Το Φιλί της Γυναίκας Αράχνης",
      "original_title": "Kiss of the Spider Woman",
      "athinorama_link": "https://www.athinorama.gr/cinema/movie/to_fili_tis_gunaikas_araxnis-10087606"
    }
  ],
  [
    {
      "greek_title": "Flow - Η Γάτα που δεν Φοβόταν το Νερό",
      "original_title": "Straume / Flow",
      "athinorama_link": "https://www.athinorama.gr/cinema/movie/flow___i_gata_pou_den_fobotan_to_nero__-10084571"
    }
  ],
  [
    {
      "greek_title": "Χάιντι: Η Διάσωση του Μικρού Λύγκα",
      "original_title": "Heidi - Die Legende vom Luchs / Heidi - Rescue of the Lynx",
      "athinorama_link": "https://www.athinorama.gr/cinema/movie/xainti_i_diasosi_tou_mikrou_lugka-10087460"
    }
  ],
  [
    {
      "greek_title": "Harvest",
      "original_title": "",
      "athinorama_link": "https://www.athinorama.gr/cinema/movie/harvest-10087183"
    }
  ],
  [
    {
      "greek_title": "Το Χειρόγραφο της Σαραγόσα",
      "original_title": "Recopis Znaleziony w Saragossie / The Saragossa Manuscript",
      "athinorama_link": "https://www.athinorama.gr/cinema/movie/to_xeirografo_tis_saragosa-10024852"
    }
  ],
  [
    {
      "greek_title": "Ως τα Χαράματα",
      "original_title": "When the Light Breaks",
      "athinorama_link": "https://www.athinorama.gr/cinema/movie/os_ta_xaramata-10087548"
    }
  ]
]